{"metrics": [{"reward_score": 803, "metric_time": 45927, "start_time": 28862, "elapsed_time_in_milliseconds": 17065, "episode": 1, "trial": 1, "phase": "training", "completion_percentage": 30, "episode_status": "Off track"}, {"reward_score": 278, "metric_time": 52107, "start_time": 45987, "elapsed_time_in_milliseconds": 6120, "episode": 2, "trial": 2, "phase": "training", "completion_percentage": 11, "episode_status": "Off track"}, {"reward_score": 89, "metric_time": 55462, "start_time": 52184, "elapsed_time_in_milliseconds": 3278, "episode": 3, "trial": 3, "phase": "training", "completion_percentage": 5, "episode_status": "Off track"}, {"reward_score": 44, "metric_time": 57440, "start_time": 55486, "elapsed_time_in_milliseconds": 1954, "episode": 4, "trial": 4, "phase": "training", "completion_percentage": 2, "episode_status": "Off track"}, {"reward_score": 148, "metric_time": 61039, "start_time": 57531, "elapsed_time_in_milliseconds": 3508, "episode": 5, "trial": 5, "phase": "training", "completion_percentage": 5, "episode_status": "Off track"}, {"reward_score": 125, "metric_time": 64464, "start_time": 61107, "elapsed_time_in_milliseconds": 3357, "episode": 6, "trial": 6, "phase": "training", "completion_percentage": 5, "episode_status": "Off track"}, {"reward_score": 68, "metric_time": 66918, "start_time": 64507, "elapsed_time_in_milliseconds": 2411, "episode": 7, "trial": 7, "phase": "training", "completion_percentage": 3, "episode_status": "Off track"}, {"reward_score": 103, "metric_time": 69663, "start_time": 66976, "elapsed_time_in_milliseconds": 2687, "episode": 8, "trial": 8, "phase": "training", "completion_percentage": 3, "episode_status": "Off track"}, {"reward_score": 57, "metric_time": 72061, "start_time": 69690, "elapsed_time_in_milliseconds": 2371, "episode": 9, "trial": 9, "phase": "training", "completion_percentage": 3, "episode_status": "Off track"}, {"reward_score": 101, "metric_time": 74868, "start_time": 72116, "elapsed_time_in_milliseconds": 2752, "episode": 10, "trial": 10, "phase": "training", "completion_percentage": 4, "episode_status": "Off track"}, {"reward_score": 65, "metric_time": 77298, "start_time": 74902, "elapsed_time_in_milliseconds": 2396, "episode": 11, "trial": 11, "phase": "training", "completion_percentage": 3, "episode_status": "Off track"}, {"reward_score": 234, "metric_time": 82499, "start_time": 77375, "elapsed_time_in_milliseconds": 5124, "episode": 12, "trial": 12, "phase": "training", "completion_percentage": 9, "episode_status": "Off track"}, {"reward_score": 217, "metric_time": 88334, "start_time": 82572, "elapsed_time_in_milliseconds": 5762, "episode": 13, "trial": 13, "phase": "training", "completion_percentage": 9, "episode_status": "Off track"}, {"reward_score": 66, "metric_time": 90595, "start_time": 88379, "elapsed_time_in_milliseconds": 2216, "episode": 14, "trial": 14, "phase": "training", "completion_percentage": 3, "episode_status": "Off track"}, {"reward_score": 93, "metric_time": 93056, "start_time": 90635, "elapsed_time_in_milliseconds": 2421, "episode": 15, "trial": 15, "phase": "training", "completion_percentage": 4, "episode_status": "Off track"}, {"reward_score": 124, "metric_time": 96734, "start_time": 93126, "elapsed_time_in_milliseconds": 3608, "episode": 16, "trial": 16, "phase": "training", "completion_percentage": 5, "episode_status": "Off track"}, {"reward_score": 68, "metric_time": 99111, "start_time": 96782, "elapsed_time_in_milliseconds": 2329, "episode": 17, "trial": 17, "phase": "training", "completion_percentage": 3, "episode_status": "Off track"}, {"reward_score": 18, "metric_time": 101517, "start_time": 99195, "elapsed_time_in_milliseconds": 2322, "episode": 18, "trial": 18, "phase": "training", "completion_percentage": 3, "episode_status": "Off track"}, {"reward_score": 344, "metric_time": 109568, "start_time": 101565, "elapsed_time_in_milliseconds": 8003, "episode": 19, "trial": 19, "phase": "training", "completion_percentage": 15, "episode_status": "Off track"}, {"reward_score": 206, "metric_time": 115173, "start_time": 109646, "elapsed_time_in_milliseconds": 5527, "episode": 20, "trial": 20, "phase": "training", "completion_percentage": 8, "episode_status": "Off track"}, {"reward_score": 316, "metric_time": 122865, "start_time": 115311, "elapsed_time_in_milliseconds": 7554, "episode": 20, "trial": 20, "phase": "evaluation", "completion_percentage": 13, "episode_status": "Off track"}, {"reward_score": 307, "metric_time": 129797, "start_time": 122909, "elapsed_time_in_milliseconds": 6888, "episode": 20, "trial": 20, "phase": "evaluation", "completion_percentage": 11, "episode_status": "Off track"}, {"reward_score": 324, "metric_time": 137330, "start_time": 129843, "elapsed_time_in_milliseconds": 7487, "episode": 20, "trial": 20, "phase": "evaluation", "completion_percentage": 13, "episode_status": "Off track"}, {"reward_score": 322, "metric_time": 144847, "start_time": 137384, "elapsed_time_in_milliseconds": 7463, "episode": 20, "trial": 20, "phase": "evaluation", "completion_percentage": 13, "episode_status": "Off track"}, {"reward_score": 327, "metric_time": 152253, "start_time": 144904, "elapsed_time_in_milliseconds": 7349, "episode": 20, "trial": 20, "phase": "evaluation", "completion_percentage": 13, "episode_status": "Off track"}, {"reward_score": 246, "metric_time": 157913, "start_time": 152297, "elapsed_time_in_milliseconds": 5616, "episode": 20, "trial": 20, "phase": "evaluation", "completion_percentage": 9, "episode_status": "Off track"}, {"reward_score": 104, "metric_time": 160836, "start_time": 157959, "elapsed_time_in_milliseconds": 2877, "episode": 21, "trial": 1, "phase": "training", "completion_percentage": 4, "episode_status": "Off track"}, {"reward_score": 97, "metric_time": 165245, "start_time": 160927, "elapsed_time_in_milliseconds": 4318, "episode": 22, "trial": 2, "phase": "training", "completion_percentage": 7, "episode_status": "Off track"}, {"reward_score": 67, "metric_time": 167525, "start_time": 165320, "elapsed_time_in_milliseconds": 2205, "episode": 23, "trial": 3, "phase": "training", "completion_percentage": 3, "episode_status": "Off track"}, {"reward_score": 147, "metric_time": 172653, "start_time": 167557, "elapsed_time_in_milliseconds": 5096, "episode": 24, "trial": 4, "phase": "training", "completion_percentage": 9, "episode_status": "Off track"}, {"reward_score": 200, "metric_time": 177863, "start_time": 172712, "elapsed_time_in_milliseconds": 5151, "episode": 25, "trial": 5, "phase": "training", "completion_percentage": 8, "episode_status": "Off track"}, {"reward_score": 155, "metric_time": 181988, "start_time": 177930, "elapsed_time_in_milliseconds": 4058, "episode": 26, "trial": 6, "phase": "training", "completion_percentage": 7, "episode_status": "Off track"}, {"reward_score": 179, "metric_time": 186713, "start_time": 182036, "elapsed_time_in_milliseconds": 4677, "episode": 27, "trial": 7, "phase": "training", "completion_percentage": 7, "episode_status": "Off track"}, {"reward_score": 40, "metric_time": 188858, "start_time": 186777, "elapsed_time_in_milliseconds": 2081, "episode": 28, "trial": 8, "phase": "training", "completion_percentage": 2, "episode_status": "Off track"}, {"reward_score": 93, "metric_time": 192580, "start_time": 188903, "elapsed_time_in_milliseconds": 3677, "episode": 29, "trial": 9, "phase": "training", "completion_percentage": 5, "episode_status": "Off track"}, {"reward_score": 121, "metric_time": 197958, "start_time": 192647, "elapsed_time_in_milliseconds": 5311, "episode": 30, "trial": 10, "phase": "training", "completion_percentage": 9, "episode_status": "Off track"}, {"reward_score": 46, "metric_time": 200252, "start_time": 197981, "elapsed_time_in_milliseconds": 2271, "episode": 31, "trial": 11, "phase": "training", "completion_percentage": 2, "episode_status": "Off track"}, {"reward_score": 93, "metric_time": 203037, "start_time": 200315, "elapsed_time_in_milliseconds": 2722, "episode": 32, "trial": 12, "phase": "training", "completion_percentage": 4, "episode_status": "Off track"}, {"reward_score": 134, "metric_time": 208781, "start_time": 203110, "elapsed_time_in_milliseconds": 5671, "episode": 33, "trial": 13, "phase": "training", "completion_percentage": 8, "episode_status": "Off track"}, {"reward_score": 99, "metric_time": 211727, "start_time": 208861, "elapsed_time_in_milliseconds": 2866, "episode": 34, "trial": 14, "phase": "training", "completion_percentage": 4, "episode_status": "Off track"}, {"reward_score": 160, "metric_time": 216111, "start_time": 211788, "elapsed_time_in_milliseconds": 4323, "episode": 35, "trial": 15, "phase": "training", "completion_percentage": 7, "episode_status": "Off track"}, {"reward_score": 170, "metric_time": 220531, "start_time": 216166, "elapsed_time_in_milliseconds": 4365, "episode": 36, "trial": 16, "phase": "training", "completion_percentage": 6, "episode_status": "Off track"}, {"reward_score": 37, "metric_time": 222325, "start_time": 220574, "elapsed_time_in_milliseconds": 1751, "episode": 37, "trial": 17, "phase": "training", "completion_percentage": 1, "episode_status": "Off track"}, {"reward_score": 208, "metric_time": 226933, "start_time": 222408, "elapsed_time_in_milliseconds": 4525, "episode": 38, "trial": 18, "phase": "training", "completion_percentage": 8, "episode_status": "Off track"}, {"reward_score": 212, "metric_time": 232259, "start_time": 226987, "elapsed_time_in_milliseconds": 5272, "episode": 39, "trial": 19, "phase": "training", "completion_percentage": 8, "episode_status": "Off track"}, {"reward_score": 145, "metric_time": 236199, "start_time": 232311, "elapsed_time_in_milliseconds": 3888, "episode": 40, "trial": 20, "phase": "training", "completion_percentage": 7, "episode_status": "Off track"}, {"reward_score": 1021, "metric_time": 257045, "start_time": 236312, "elapsed_time_in_milliseconds": 20733, "episode": 40, "trial": 20, "phase": "evaluation", "completion_percentage": 37, "episode_status": "Off track"}, {"reward_score": 967, "metric_time": 277839, "start_time": 257103, "elapsed_time_in_milliseconds": 20736, "episode": 40, "trial": 20, "phase": "evaluation", "completion_percentage": 37, "episode_status": "Off track"}, {"reward_score": 1011, "metric_time": 298582, "start_time": 277916, "elapsed_time_in_milliseconds": 20666, "episode": 40, "trial": 20, "phase": "evaluation", "completion_percentage": 37, "episode_status": "Off track"}, {"reward_score": 970, "metric_time": 319306, "start_time": 298660, "elapsed_time_in_milliseconds": 20646, "episode": 40, "trial": 20, "phase": "evaluation", "completion_percentage": 37, "episode_status": "Off track"}, {"reward_score": 1052, "metric_time": 340916, "start_time": 319381, "elapsed_time_in_milliseconds": 21535, "episode": 40, "trial": 20, "phase": "evaluation", "completion_percentage": 37, "episode_status": "Off track"}, {"reward_score": 994, "metric_time": 362517, "start_time": 340978, "elapsed_time_in_milliseconds": 21539, "episode": 40, "trial": 20, "phase": "evaluation", "completion_percentage": 37, "episode_status": "Off track"}, {"reward_score": 935, "metric_time": 383062, "start_time": 362577, "elapsed_time_in_milliseconds": 20485, "episode": 41, "trial": 1, "phase": "training", "completion_percentage": 37, "episode_status": "Off track"}, {"reward_score": 848, "metric_time": 402506, "start_time": 383103, "elapsed_time_in_milliseconds": 19403, "episode": 42, "trial": 2, "phase": "training", "completion_percentage": 34, "episode_status": "Off track"}, {"reward_score": 204, "metric_time": 407975, "start_time": 402582, "elapsed_time_in_milliseconds": 5393, "episode": 43, "trial": 3, "phase": "training", "completion_percentage": 9, "episode_status": "Off track"}, {"reward_score": 319, "metric_time": 416125, "start_time": 408057, "elapsed_time_in_milliseconds": 8068, "episode": 44, "trial": 4, "phase": "training", "completion_percentage": 13, "episode_status": "Off track"}, {"reward_score": 443, "metric_time": 426849, "start_time": 416176, "elapsed_time_in_milliseconds": 10673, "episode": 45, "trial": 5, "phase": "training", "completion_percentage": 19, "episode_status": "Off track"}, {"reward_score": 201, "metric_time": 432173, "start_time": 426917, "elapsed_time_in_milliseconds": 5256, "episode": 46, "trial": 6, "phase": "training", "completion_percentage": 9, "episode_status": "Off track"}, {"reward_score": 644, "metric_time": 447796, "start_time": 432255, "elapsed_time_in_milliseconds": 15541, "episode": 47, "trial": 7, "phase": "training", "completion_percentage": 27, "episode_status": "Off track"}, {"reward_score": 345, "metric_time": 457727, "start_time": 447845, "elapsed_time_in_milliseconds": 9882, "episode": 48, "trial": 8, "phase": "training", "completion_percentage": 17, "episode_status": "Off track"}, {"reward_score": 144, "metric_time": 461717, "start_time": 457767, "elapsed_time_in_milliseconds": 3950, "episode": 49, "trial": 9, "phase": "training", "completion_percentage": 6, "episode_status": "Off track"}, {"reward_score": 271, "metric_time": 467917, "start_time": 461775, "elapsed_time_in_milliseconds": 6142, "episode": 50, "trial": 10, "phase": "training", "completion_percentage": 11, "episode_status": "Off track"}, {"reward_score": 38, "metric_time": 469790, "start_time": 467969, "elapsed_time_in_milliseconds": 1821, "episode": 51, "trial": 11, "phase": "training", "completion_percentage": 2, "episode_status": "Off track"}, {"reward_score": 290, "metric_time": 476402, "start_time": 469852, "elapsed_time_in_milliseconds": 6550, "episode": 52, "trial": 12, "phase": "training", "completion_percentage": 11, "episode_status": "Off track"}, {"reward_score": 474, "metric_time": 486528, "start_time": 476438, "elapsed_time_in_milliseconds": 10090, "episode": 53, "trial": 13, "phase": "training", "completion_percentage": 20, "episode_status": "Off track"}, {"reward_score": 160, "metric_time": 491189, "start_time": 486575, "elapsed_time_in_milliseconds": 4614, "episode": 54, "trial": 14, "phase": "training", "completion_percentage": 7, "episode_status": "Off track"}, {"reward_score": 113, "metric_time": 494320, "start_time": 491236, "elapsed_time_in_milliseconds": 3084, "episode": 55, "trial": 15, "phase": "training", "completion_percentage": 4, "episode_status": "Off track"}, {"reward_score": 120, "metric_time": 498265, "start_time": 494396, "elapsed_time_in_milliseconds": 3869, "episode": 56, "trial": 16, "phase": "training", "completion_percentage": 6, "episode_status": "Off track"}, {"reward_score": 46, "metric_time": 500432, "start_time": 498307, "elapsed_time_in_milliseconds": 2125, "episode": 57, "trial": 17, "phase": "training", "completion_percentage": 2, "episode_status": "Off track"}, {"reward_score": 100, "metric_time": 504047, "start_time": 500508, "elapsed_time_in_milliseconds": 3539, "episode": 58, "trial": 18, "phase": "training", "completion_percentage": 4, "episode_status": "Off track"}, {"reward_score": 169, "metric_time": 509530, "start_time": 504112, "elapsed_time_in_milliseconds": 5418, "episode": 59, "trial": 19, "phase": "training", "completion_percentage": 10, "episode_status": "Off track"}, {"reward_score": 43, "metric_time": 511713, "start_time": 509581, "elapsed_time_in_milliseconds": 2132, "episode": 60, "trial": 20, "phase": "training", "completion_percentage": 2, "episode_status": "Off track"}, {"reward_score": 2180, "metric_time": 554268, "start_time": 511912, "elapsed_time_in_milliseconds": 42356, "episode": 60, "trial": 20, "phase": "evaluation", "completion_percentage": 80, "episode_status": "Off track"}, {"reward_score": 1613, "metric_time": 585115, "start_time": 554299, "elapsed_time_in_milliseconds": 30816, "episode": 60, "trial": 20, "phase": "evaluation", "completion_percentage": 57, "episode_status": "Off track"}, {"reward_score": 2184, "metric_time": 627459, "start_time": 585174, "elapsed_time_in_milliseconds": 42285, "episode": 60, "trial": 20, "phase": "evaluation", "completion_percentage": 79, "episode_status": "Off track"}, {"reward_score": 1147, "metric_time": 650729, "start_time": 627522, "elapsed_time_in_milliseconds": 23207, "episode": 60, "trial": 20, "phase": "evaluation", "completion_percentage": 43, "episode_status": "Off track"}, {"reward_score": 2186, "metric_time": 692918, "start_time": 650782, "elapsed_time_in_milliseconds": 42136, "episode": 60, "trial": 20, "phase": "evaluation", "completion_percentage": 79, "episode_status": "Off track"}, {"reward_score": 2179, "metric_time": 734905, "start_time": 692975, "elapsed_time_in_milliseconds": 41930, "episode": 60, "trial": 20, "phase": "evaluation", "completion_percentage": 79, "episode_status": "Off track"}, {"reward_score": 233, "metric_time": 740446, "start_time": 734979, "elapsed_time_in_milliseconds": 5467, "episode": 61, "trial": 1, "phase": "training", "completion_percentage": 9, "episode_status": "Off track"}, {"reward_score": 99, "metric_time": 743655, "start_time": 740511, "elapsed_time_in_milliseconds": 3144, "episode": 62, "trial": 2, "phase": "training", "completion_percentage": 4, "episode_status": "Off track"}, {"reward_score": 194, "metric_time": 748972, "start_time": 743694, "elapsed_time_in_milliseconds": 5278, "episode": 63, "trial": 3, "phase": "training", "completion_percentage": 8, "episode_status": "Off track"}, {"reward_score": 686, "metric_time": 765254, "start_time": 749073, "elapsed_time_in_milliseconds": 16181, "episode": 64, "trial": 4, "phase": "training", "completion_percentage": 29, "episode_status": "Off track"}, {"reward_score": 236, "metric_time": 771739, "start_time": 765317, "elapsed_time_in_milliseconds": 6422, "episode": 65, "trial": 5, "phase": "training", "completion_percentage": 10, "episode_status": "Off track"}, {"reward_score": 189, "metric_time": 776241, "start_time": 771790, "elapsed_time_in_milliseconds": 4451, "episode": 66, "trial": 6, "phase": "training", "completion_percentage": 8, "episode_status": "Off track"}, {"reward_score": 200, "metric_time": 781197, "start_time": 776313, "elapsed_time_in_milliseconds": 4884, "episode": 67, "trial": 7, "phase": "training", "completion_percentage": 8, "episode_status": "Off track"}, {"reward_score": 89, "metric_time": 785727, "start_time": 781234, "elapsed_time_in_milliseconds": 4493, "episode": 68, "trial": 8, "phase": "training", "completion_percentage": 7, "episode_status": "Off track"}, {"reward_score": 241, "metric_time": 792068, "start_time": 785774, "elapsed_time_in_milliseconds": 6294, "episode": 69, "trial": 9, "phase": "training", "completion_percentage": 10, "episode_status": "Off track"}, {"reward_score": 333, "metric_time": 799270, "start_time": 792104, "elapsed_time_in_milliseconds": 7166, "episode": 70, "trial": 10, "phase": "training", "completion_percentage": 13, "episode_status": "Off track"}, {"reward_score": 84, "metric_time": 802448, "start_time": 799313, "elapsed_time_in_milliseconds": 3135, "episode": 71, "trial": 11, "phase": "training", "completion_percentage": 4, "episode_status": "Off track"}, {"reward_score": 616, "metric_time": 816128, "start_time": 802515, "elapsed_time_in_milliseconds": 13613, "episode": 72, "trial": 12, "phase": "training", "completion_percentage": 23, "episode_status": "Off track"}, {"reward_score": 424, "metric_time": 826238, "start_time": 816199, "elapsed_time_in_milliseconds": 10039, "episode": 73, "trial": 13, "phase": "training", "completion_percentage": 17, "episode_status": "Off track"}, {"reward_score": 69, "metric_time": 828838, "start_time": 826316, "elapsed_time_in_milliseconds": 2522, "episode": 74, "trial": 14, "phase": "training", "completion_percentage": 3, "episode_status": "Off track"}, {"reward_score": 194, "metric_time": 834609, "start_time": 828917, "elapsed_time_in_milliseconds": 5692, "episode": 75, "trial": 15, "phase": "training", "completion_percentage": 8, "episode_status": "Off track"}, {"reward_score": 171, "metric_time": 838924, "start_time": 834651, "elapsed_time_in_milliseconds": 4273, "episode": 76, "trial": 16, "phase": "training", "completion_percentage": 6, "episode_status": "Off track"}, {"reward_score": 96, "metric_time": 841660, "start_time": 838998, "elapsed_time_in_milliseconds": 2662, "episode": 77, "trial": 17, "phase": "training", "completion_percentage": 3, "episode_status": "Off track"}, {"reward_score": 76, "metric_time": 844665, "start_time": 841695, "elapsed_time_in_milliseconds": 2970, "episode": 78, "trial": 18, "phase": "training", "completion_percentage": 3, "episode_status": "Off track"}, {"reward_score": 88, "metric_time": 846843, "start_time": 844707, "elapsed_time_in_milliseconds": 2136, "episode": 79, "trial": 19, "phase": "training", "completion_percentage": 3, "episode_status": "Off track"}, {"reward_score": 302, "metric_time": 856188, "start_time": 846929, "elapsed_time_in_milliseconds": 9259, "episode": 80, "trial": 20, "phase": "training", "completion_percentage": 14, "episode_status": "Off track"}, {"reward_score": 1494, "metric_time": 887602, "start_time": 856376, "elapsed_time_in_milliseconds": 31226, "episode": 80, "trial": 20, "phase": "evaluation", "completion_percentage": 57, "episode_status": "Off track"}, {"reward_score": 2167, "metric_time": 931649, "start_time": 887642, "elapsed_time_in_milliseconds": 44007, "episode": 80, "trial": 20, "phase": "evaluation", "completion_percentage": 81, "episode_status": "Off track"}, {"reward_score": 254, "metric_time": 937651, "start_time": 931710, "elapsed_time_in_milliseconds": 5941, "episode": 80, "trial": 20, "phase": "evaluation", "completion_percentage": 9, "episode_status": "Off track"}, {"reward_score": 1167, "metric_time": 961593, "start_time": 937704, "elapsed_time_in_milliseconds": 23889, "episode": 80, "trial": 20, "phase": "evaluation", "completion_percentage": 43, "episode_status": "Off track"}, {"reward_score": 2223, "metric_time": 1005400, "start_time": 961648, "elapsed_time_in_milliseconds": 43752, "episode": 80, "trial": 20, "phase": "evaluation", "completion_percentage": 80, "episode_status": "Off track"}, {"reward_score": 1148, "metric_time": 1029536, "start_time": 1005438, "elapsed_time_in_milliseconds": 24098, "episode": 80, "trial": 20, "phase": "evaluation", "completion_percentage": 44, "episode_status": "Off track"}, {"reward_score": 154, "metric_time": 1033206, "start_time": 1029583, "elapsed_time_in_milliseconds": 3623, "episode": 81, "trial": 1, "phase": "training", "completion_percentage": 6, "episode_status": "Off track"}, {"reward_score": 442, "metric_time": 1043915, "start_time": 1033262, "elapsed_time_in_milliseconds": 10653, "episode": 82, "trial": 2, "phase": "training", "completion_percentage": 18, "episode_status": "Off track"}, {"reward_score": 766, "metric_time": 1059867, "start_time": 1043994, "elapsed_time_in_milliseconds": 15873, "episode": 83, "trial": 3, "phase": "training", "completion_percentage": 27, "episode_status": "Off track"}, {"reward_score": 749, "metric_time": 1077930, "start_time": 1059908, "elapsed_time_in_milliseconds": 18022, "episode": 84, "trial": 4, "phase": "training", "completion_percentage": 32, "episode_status": "Off track"}, {"reward_score": 412, "metric_time": 1088141, "start_time": 1077967, "elapsed_time_in_milliseconds": 10174, "episode": 85, "trial": 5, "phase": "training", "completion_percentage": 17, "episode_status": "Off track"}, {"reward_score": 670, "metric_time": 1102937, "start_time": 1088184, "elapsed_time_in_milliseconds": 14753, "episode": 86, "trial": 6, "phase": "training", "completion_percentage": 27, "episode_status": "Off track"}, {"reward_score": 165, "metric_time": 1108268, "start_time": 1102967, "elapsed_time_in_milliseconds": 5301, "episode": 87, "trial": 7, "phase": "training", "completion_percentage": 8, "episode_status": "Off track"}, {"reward_score": 94, "metric_time": 1111112, "start_time": 1108338, "elapsed_time_in_milliseconds": 2774, "episode": 88, "trial": 8, "phase": "training", "completion_percentage": 4, "episode_status": "Off track"}, {"reward_score": 327, "metric_time": 1119566, "start_time": 1111181, "elapsed_time_in_milliseconds": 8385, "episode": 89, "trial": 9, "phase": "training", "completion_percentage": 13, "episode_status": "Off track"}, {"reward_score": 192, "metric_time": 1124663, "start_time": 1119649, "elapsed_time_in_milliseconds": 5014, "episode": 90, "trial": 10, "phase": "training", "completion_percentage": 7, "episode_status": "Off track"}, {"reward_score": 48, "metric_time": 1126924, "start_time": 1124700, "elapsed_time_in_milliseconds": 2224, "episode": 91, "trial": 11, "phase": "training", "completion_percentage": 2, "episode_status": "Off track"}, {"reward_score": 169, "metric_time": 1133242, "start_time": 1126994, "elapsed_time_in_milliseconds": 6248, "episode": 92, "trial": 12, "phase": "training", "completion_percentage": 10, "episode_status": "Off track"}, {"reward_score": 191, "metric_time": 1139523, "start_time": 1133312, "elapsed_time_in_milliseconds": 6211, "episode": 93, "trial": 13, "phase": "training", "completion_percentage": 10, "episode_status": "Off track"}, {"reward_score": 307, "metric_time": 1148104, "start_time": 1139598, "elapsed_time_in_milliseconds": 8506, "episode": 94, "trial": 14, "phase": "training", "completion_percentage": 14, "episode_status": "Off track"}, {"reward_score": 154, "metric_time": 1151858, "start_time": 1148178, "elapsed_time_in_milliseconds": 3680, "episode": 95, "trial": 15, "phase": "training", "completion_percentage": 6, "episode_status": "Off track"}, {"reward_score": 481, "metric_time": 1160396, "start_time": 1151907, "elapsed_time_in_milliseconds": 8489, "episode": 96, "trial": 16, "phase": "training", "completion_percentage": 16, "episode_status": "Off track"}, {"reward_score": 170, "metric_time": 1164330, "start_time": 1160446, "elapsed_time_in_milliseconds": 3884, "episode": 97, "trial": 17, "phase": "training", "completion_percentage": 9, "episode_status": "Off track"}, {"reward_score": 145, "metric_time": 1168384, "start_time": 1164392, "elapsed_time_in_milliseconds": 3992, "episode": 98, "trial": 18, "phase": "training", "completion_percentage": 5, "episode_status": "Off track"}, {"reward_score": 146, "metric_time": 1171800, "start_time": 1168440, "elapsed_time_in_milliseconds": 3360, "episode": 99, "trial": 19, "phase": "training", "completion_percentage": 6, "episode_status": "Off track"}, {"reward_score": 485, "metric_time": 1183576, "start_time": 1171860, "elapsed_time_in_milliseconds": 11716, "episode": 100, "trial": 20, "phase": "training", "completion_percentage": 21, "episode_status": "Off track"}, {"reward_score": 235, "metric_time": 1189587, "start_time": 1183708, "elapsed_time_in_milliseconds": 5879, "episode": 100, "trial": 20, "phase": "evaluation", "completion_percentage": 12, "episode_status": "Off track"}, {"reward_score": 1804, "metric_time": 1231510, "start_time": 1189626, "elapsed_time_in_milliseconds": 41884, "episode": 100, "trial": 20, "phase": "evaluation", "completion_percentage": 80, "episode_status": "Off track"}, {"reward_score": 289, "metric_time": 1239905, "start_time": 1231574, "elapsed_time_in_milliseconds": 8331, "episode": 100, "trial": 20, "phase": "evaluation", "completion_percentage": 17, "episode_status": "Off track"}, {"reward_score": 698, "metric_time": 1261926, "start_time": 1239978, "elapsed_time_in_milliseconds": 21948, "episode": 100, "trial": 20, "phase": "evaluation", "completion_percentage": 46, "episode_status": "Off track"}, {"reward_score": 271, "metric_time": 1269908, "start_time": 1261994, "elapsed_time_in_milliseconds": 7914, "episode": 100, "trial": 20, "phase": "evaluation", "completion_percentage": 17, "episode_status": "Off track"}, {"reward_score": 879, "metric_time": 1291908, "start_time": 1269987, "elapsed_time_in_milliseconds": 21921, "episode": 100, "trial": 20, "phase": "evaluation", "completion_percentage": 44, "episode_status": "Off track"}, {"reward_score": 966, "metric_time": 1313846, "start_time": 1291960, "elapsed_time_in_milliseconds": 21886, "episode": 101, "trial": 1, "phase": "training", "completion_percentage": 41, "episode_status": "Off track"}, {"reward_score": 420, "metric_time": 1323396, "start_time": 1313911, "elapsed_time_in_milliseconds": 9485, "episode": 102, "trial": 2, "phase": "training", "completion_percentage": 19, "episode_status": "Off track"}, {"reward_score": 1159, "metric_time": 1349908, "start_time": 1323447, "elapsed_time_in_milliseconds": 26461, "episode": 103, "trial": 3, "phase": "training", "completion_percentage": 47, "episode_status": "Off track"}, {"reward_score": 608, "metric_time": 1363712, "start_time": 1349980, "elapsed_time_in_milliseconds": 13732, "episode": 104, "trial": 4, "phase": "training", "completion_percentage": 24, "episode_status": "Off track"}, {"reward_score": 351, "metric_time": 1372007, "start_time": 1363784, "elapsed_time_in_milliseconds": 8223, "episode": 105, "trial": 5, "phase": "training", "completion_percentage": 14, "episode_status": "Off track"}, {"reward_score": 358, "metric_time": 1380118, "start_time": 1372060, "elapsed_time_in_milliseconds": 8058, "episode": 106, "trial": 6, "phase": "training", "completion_percentage": 15, "episode_status": "Off track"}, {"reward_score": 1222, "metric_time": 1407000, "start_time": 1380184, "elapsed_time_in_milliseconds": 26816, "episode": 107, "trial": 7, "phase": "training", "completion_percentage": 49, "episode_status": "Off track"}, {"reward_score": 386, "metric_time": 1417581, "start_time": 1407040, "elapsed_time_in_milliseconds": 10541, "episode": 108, "trial": 8, "phase": "training", "completion_percentage": 20, "episode_status": "Off track"}, {"reward_score": 233, "metric_time": 1426272, "start_time": 1417664, "elapsed_time_in_milliseconds": 8608, "episode": 109, "trial": 9, "phase": "training", "completion_percentage": 16, "episode_status": "Off track"}, {"reward_score": 183, "metric_time": 1431124, "start_time": 1426302, "elapsed_time_in_milliseconds": 4822, "episode": 110, "trial": 10, "phase": "training", "completion_percentage": 7, "episode_status": "Off track"}, {"reward_score": 648, "metric_time": 1447596, "start_time": 1431193, "elapsed_time_in_milliseconds": 16403, "episode": 111, "trial": 11, "phase": "training", "completion_percentage": 30, "episode_status": "Off track"}, {"reward_score": 657, "metric_time": 1462069, "start_time": 1447653, "elapsed_time_in_milliseconds": 14416, "episode": 112, "trial": 12, "phase": "training", "completion_percentage": 26, "episode_status": "Off track"}, {"reward_score": 383, "metric_time": 1470649, "start_time": 1462128, "elapsed_time_in_milliseconds": 8521, "episode": 113, "trial": 13, "phase": "training", "completion_percentage": 15, "episode_status": "Off track"}, {"reward_score": 391, "metric_time": 1479934, "start_time": 1470727, "elapsed_time_in_milliseconds": 9207, "episode": 114, "trial": 14, "phase": "training", "completion_percentage": 15, "episode_status": "Off track"}, {"reward_score": 254, "metric_time": 1486521, "start_time": 1479982, "elapsed_time_in_milliseconds": 6539, "episode": 115, "trial": 15, "phase": "training", "completion_percentage": 10, "episode_status": "Off track"}, {"reward_score": 55, "metric_time": 1488927, "start_time": 1486564, "elapsed_time_in_milliseconds": 2363, "episode": 116, "trial": 16, "phase": "training", "completion_percentage": 3, "episode_status": "Off track"}, {"reward_score": 216, "metric_time": 1494724, "start_time": 1488973, "elapsed_time_in_milliseconds": 5751, "episode": 117, "trial": 17, "phase": "training", "completion_percentage": 9, "episode_status": "Off track"}, {"reward_score": 155, "metric_time": 1498343, "start_time": 1494769, "elapsed_time_in_milliseconds": 3574, "episode": 118, "trial": 18, "phase": "training", "completion_percentage": 5, "episode_status": "Off track"}, {"reward_score": 234, "metric_time": 1504520, "start_time": 1498390, "elapsed_time_in_milliseconds": 6130, "episode": 119, "trial": 19, "phase": "training", "completion_percentage": 10, "episode_status": "Off track"}, {"reward_score": 978, "metric_time": 1525998, "start_time": 1504577, "elapsed_time_in_milliseconds": 21421, "episode": 120, "trial": 20, "phase": "training", "completion_percentage": 40, "episode_status": "Off track"}, {"reward_score": 377, "metric_time": 1534991, "start_time": 1526146, "elapsed_time_in_milliseconds": 8845, "episode": 120, "trial": 20, "phase": "evaluation", "completion_percentage": 17, "episode_status": "Off track"}, {"reward_score": 255, "metric_time": 1540460, "start_time": 1535042, "elapsed_time_in_milliseconds": 5418, "episode": 120, "trial": 20, "phase": "evaluation", "completion_percentage": 10, "episode_status": "Off track"}, {"reward_score": 258, "metric_time": 1548333, "start_time": 1540508, "elapsed_time_in_milliseconds": 7825, "episode": 120, "trial": 20, "phase": "evaluation", "completion_percentage": 16, "episode_status": "Off track"}, {"reward_score": 269, "metric_time": 1554333, "start_time": 1548394, "elapsed_time_in_milliseconds": 5939, "episode": 120, "trial": 20, "phase": "evaluation", "completion_percentage": 11, "episode_status": "Off track"}, {"reward_score": 2087, "metric_time": 1596392, "start_time": 1554377, "elapsed_time_in_milliseconds": 42015, "episode": 120, "trial": 20, "phase": "evaluation", "completion_percentage": 81, "episode_status": "Off track"}, {"reward_score": 254, "metric_time": 1602529, "start_time": 1596468, "elapsed_time_in_milliseconds": 6061, "episode": 120, "trial": 20, "phase": "evaluation", "completion_percentage": 12, "episode_status": "Off track"}, {"reward_score": 251, "metric_time": 1610395, "start_time": 1602582, "elapsed_time_in_milliseconds": 7813, "episode": 121, "trial": 1, "phase": "training", "completion_percentage": 13, "episode_status": "Off track"}, {"reward_score": 715, "metric_time": 1627585, "start_time": 1610462, "elapsed_time_in_milliseconds": 17123, "episode": 122, "trial": 2, "phase": "training", "completion_percentage": 32, "episode_status": "Off track"}, {"reward_score": 819, "metric_time": 1644675, "start_time": 1627648, "elapsed_time_in_milliseconds": 17027, "episode": 123, "trial": 3, "phase": "training", "completion_percentage": 33, "episode_status": "Off track"}, {"reward_score": 704, "metric_time": 1659312, "start_time": 1644722, "elapsed_time_in_milliseconds": 14590, "episode": 124, "trial": 4, "phase": "training", "completion_percentage": 27, "episode_status": "Off track"}, {"reward_score": 549, "metric_time": 1672403, "start_time": 1659395, "elapsed_time_in_milliseconds": 13008, "episode": 125, "trial": 5, "phase": "training", "completion_percentage": 26, "episode_status": "Off track"}, {"reward_score": 431, "metric_time": 1681478, "start_time": 1672440, "elapsed_time_in_milliseconds": 9038, "episode": 126, "trial": 6, "phase": "training", "completion_percentage": 18, "episode_status": "Off track"}, {"reward_score": 340, "metric_time": 1692344, "start_time": 1681513, "elapsed_time_in_milliseconds": 10831, "episode": 127, "trial": 7, "phase": "training", "completion_percentage": 19, "episode_status": "Off track"}, {"reward_score": 305, "metric_time": 1701214, "start_time": 1692388, "elapsed_time_in_milliseconds": 8826, "episode": 128, "trial": 8, "phase": "training", "completion_percentage": 14, "episode_status": "Off track"}, {"reward_score": 978, "metric_time": 1723667, "start_time": 1701247, "elapsed_time_in_milliseconds": 22420, "episode": 129, "trial": 9, "phase": "training", "completion_percentage": 41, "episode_status": "Off track"}, {"reward_score": 90, "metric_time": 1726836, "start_time": 1723705, "elapsed_time_in_milliseconds": 3131, "episode": 130, "trial": 10, "phase": "training", "completion_percentage": 4, "episode_status": "Off track"}, {"reward_score": 391, "metric_time": 1736273, "start_time": 1726910, "elapsed_time_in_milliseconds": 9363, "episode": 131, "trial": 11, "phase": "training", "completion_percentage": 19, "episode_status": "Off track"}, {"reward_score": 293, "metric_time": 1742988, "start_time": 1736305, "elapsed_time_in_milliseconds": 6683, "episode": 132, "trial": 12, "phase": "training", "completion_percentage": 13, "episode_status": "Off track"}, {"reward_score": 523, "metric_time": 1754868, "start_time": 1743047, "elapsed_time_in_milliseconds": 11821, "episode": 133, "trial": 13, "phase": "training", "completion_percentage": 20, "episode_status": "Off track"}, {"reward_score": 388, "metric_time": 1764347, "start_time": 1754931, "elapsed_time_in_milliseconds": 9416, "episode": 134, "trial": 14, "phase": "training", "completion_percentage": 15, "episode_status": "Off track"}, {"reward_score": 249, "metric_time": 1770725, "start_time": 1764379, "elapsed_time_in_milliseconds": 6346, "episode": 135, "trial": 15, "phase": "training", "completion_percentage": 11, "episode_status": "Off track"}, {"reward_score": 127, "metric_time": 1774333, "start_time": 1770773, "elapsed_time_in_milliseconds": 3560, "episode": 136, "trial": 16, "phase": "training", "completion_percentage": 5, "episode_status": "Off track"}, {"reward_score": 272, "metric_time": 1781264, "start_time": 1774378, "elapsed_time_in_milliseconds": 6886, "episode": 137, "trial": 17, "phase": "training", "completion_percentage": 13, "episode_status": "Off track"}, {"reward_score": 298, "metric_time": 1789793, "start_time": 1781313, "elapsed_time_in_milliseconds": 8480, "episode": 138, "trial": 18, "phase": "training", "completion_percentage": 13, "episode_status": "Off track"}, {"reward_score": 259, "metric_time": 1798594, "start_time": 1789852, "elapsed_time_in_milliseconds": 8742, "episode": 139, "trial": 19, "phase": "training", "completion_percentage": 19, "episode_status": "Off track"}, {"reward_score": 428, "metric_time": 1808736, "start_time": 1798646, "elapsed_time_in_milliseconds": 10090, "episode": 140, "trial": 20, "phase": "training", "completion_percentage": 18, "episode_status": "Off track"}, {"reward_score": 960, "metric_time": 1830212, "start_time": 1808932, "elapsed_time_in_milliseconds": 21280, "episode": 140, "trial": 20, "phase": "evaluation", "completion_percentage": 43, "episode_status": "Off track"}, {"reward_score": 253, "metric_time": 1835602, "start_time": 1830251, "elapsed_time_in_milliseconds": 5351, "episode": 140, "trial": 20, "phase": "evaluation", "completion_percentage": 10, "episode_status": "Off track"}, {"reward_score": 1087, "metric_time": 1858978, "start_time": 1835672, "elapsed_time_in_milliseconds": 23306, "episode": 140, "trial": 20, "phase": "evaluation", "completion_percentage": 46, "episode_status": "Off track"}, {"reward_score": 912, "metric_time": 1880468, "start_time": 1859042, "elapsed_time_in_milliseconds": 21426, "episode": 140, "trial": 20, "phase": "evaluation", "completion_percentage": 43, "episode_status": "Off track"}, {"reward_score": 1102, "metric_time": 1903132, "start_time": 1880536, "elapsed_time_in_milliseconds": 22596, "episode": 140, "trial": 20, "phase": "evaluation", "completion_percentage": 45, "episode_status": "Off track"}, {"reward_score": 236, "metric_time": 1908129, "start_time": 1903186, "elapsed_time_in_milliseconds": 4943, "episode": 140, "trial": 20, "phase": "evaluation", "completion_percentage": 10, "episode_status": "Off track"}, {"reward_score": 1234, "metric_time": 1934679, "start_time": 1908182, "elapsed_time_in_milliseconds": 26497, "episode": 141, "trial": 1, "phase": "training", "completion_percentage": 52, "episode_status": "Off track"}, {"reward_score": 1784, "metric_time": 1971782, "start_time": 1934720, "elapsed_time_in_milliseconds": 37062, "episode": 142, "trial": 2, "phase": "training", "completion_percentage": 73, "episode_status": "Off track"}, {"reward_score": 1159, "metric_time": 1998787, "start_time": 1971853, "elapsed_time_in_milliseconds": 26934, "episode": 143, "trial": 3, "phase": "training", "completion_percentage": 50, "episode_status": "Off track"}, {"reward_score": 722, "metric_time": 2015128, "start_time": 1998868, "elapsed_time_in_milliseconds": 16260, "episode": 144, "trial": 4, "phase": "training", "completion_percentage": 30, "episode_status": "Off track"}, {"reward_score": 629, "metric_time": 2031354, "start_time": 2015204, "elapsed_time_in_milliseconds": 16150, "episode": 145, "trial": 5, "phase": "training", "completion_percentage": 29, "episode_status": "Off track"}, {"reward_score": 406, "metric_time": 2040678, "start_time": 2031407, "elapsed_time_in_milliseconds": 9271, "episode": 146, "trial": 6, "phase": "training", "completion_percentage": 18, "episode_status": "Off track"}, {"reward_score": 402, "metric_time": 2051254, "start_time": 2040712, "elapsed_time_in_milliseconds": 10542, "episode": 147, "trial": 7, "phase": "training", "completion_percentage": 21, "episode_status": "Off track"}, {"reward_score": 108, "metric_time": 2054133, "start_time": 2051344, "elapsed_time_in_milliseconds": 2789, "episode": 148, "trial": 8, "phase": "training", "completion_percentage": 5, "episode_status": "Off track"}, {"reward_score": 349, "metric_time": 2062924, "start_time": 2054185, "elapsed_time_in_milliseconds": 8739, "episode": 149, "trial": 9, "phase": "training", "completion_percentage": 16, "episode_status": "Off track"}, {"reward_score": 150, "metric_time": 2067796, "start_time": 2062996, "elapsed_time_in_milliseconds": 4800, "episode": 150, "trial": 10, "phase": "training", "completion_percentage": 7, "episode_status": "Off track"}, {"reward_score": 660, "metric_time": 2084385, "start_time": 2067855, "elapsed_time_in_milliseconds": 16530, "episode": 151, "trial": 11, "phase": "training", "completion_percentage": 30, "episode_status": "Off track"}, {"reward_score": 659, "metric_time": 2099204, "start_time": 2084443, "elapsed_time_in_milliseconds": 14761, "episode": 152, "trial": 12, "phase": "training", "completion_percentage": 26, "episode_status": "Off track"}, {"reward_score": 522, "metric_time": 2111220, "start_time": 2099261, "elapsed_time_in_milliseconds": 11959, "episode": 153, "trial": 13, "phase": "training", "completion_percentage": 19, "episode_status": "Off track"}, {"reward_score": 378, "metric_time": 2120385, "start_time": 2111279, "elapsed_time_in_milliseconds": 9106, "episode": 154, "trial": 14, "phase": "training", "completion_percentage": 15, "episode_status": "Off track"}, {"reward_score": 167, "metric_time": 2124882, "start_time": 2120472, "elapsed_time_in_milliseconds": 4410, "episode": 155, "trial": 15, "phase": "training", "completion_percentage": 7, "episode_status": "Off track"}, {"reward_score": 201, "metric_time": 2130000, "start_time": 2124940, "elapsed_time_in_milliseconds": 5060, "episode": 156, "trial": 16, "phase": "training", "completion_percentage": 8, "episode_status": "Off track"}, {"reward_score": 261, "metric_time": 2136448, "start_time": 2130054, "elapsed_time_in_milliseconds": 6394, "episode": 157, "trial": 17, "phase": "training", "completion_percentage": 11, "episode_status": "Off track"}, {"reward_score": 168, "metric_time": 2140847, "start_time": 2136514, "elapsed_time_in_milliseconds": 4333, "episode": 158, "trial": 18, "phase": "training", "completion_percentage": 6, "episode_status": "Off track"}, {"reward_score": 111, "metric_time": 2143450, "start_time": 2140932, "elapsed_time_in_milliseconds": 2518, "episode": 159, "trial": 19, "phase": "training", "completion_percentage": 4, "episode_status": "Off track"}, {"reward_score": 1153, "metric_time": 2166553, "start_time": 2143537, "elapsed_time_in_milliseconds": 23016, "episode": 160, "trial": 20, "phase": "training", "completion_percentage": 44, "episode_status": "Off track"}, {"reward_score": 2280, "metric_time": 2215715, "start_time": 2166665, "elapsed_time_in_milliseconds": 49050, "episode": 160, "trial": 20, "phase": "evaluation", "completion_percentage": 100, "episode_status": "Lap complete"}, {"reward_score": 240, "metric_time": 2221248, "start_time": 2215803, "elapsed_time_in_milliseconds": 5445, "episode": 160, "trial": 20, "phase": "evaluation", "completion_percentage": 11, "episode_status": "Off track"}, {"reward_score": 2057, "metric_time": 2262916, "start_time": 2221315, "elapsed_time_in_milliseconds": 41601, "episode": 160, "trial": 20, "phase": "evaluation", "completion_percentage": 80, "episode_status": "Off track"}, {"reward_score": 783, "metric_time": 2283681, "start_time": 2262983, "elapsed_time_in_milliseconds": 20698, "episode": 160, "trial": 20, "phase": "evaluation", "completion_percentage": 44, "episode_status": "Off track"}, {"reward_score": 2223, "metric_time": 2327518, "start_time": 2283730, "elapsed_time_in_milliseconds": 43788, "episode": 160, "trial": 20, "phase": "evaluation", "completion_percentage": 81, "episode_status": "Off track"}, {"reward_score": 2278, "metric_time": 2374147, "start_time": 2327600, "elapsed_time_in_milliseconds": 46547, "episode": 160, "trial": 20, "phase": "evaluation", "completion_percentage": 92, "episode_status": "Off track"}, {"reward_score": 975, "metric_time": 2394535, "start_time": 2374200, "elapsed_time_in_milliseconds": 20335, "episode": 161, "trial": 1, "phase": "training", "completion_percentage": 37, "episode_status": "Off track"}, {"reward_score": 1927, "metric_time": 2434987, "start_time": 2394601, "elapsed_time_in_milliseconds": 40386, "episode": 162, "trial": 2, "phase": "training", "completion_percentage": 75, "episode_status": "Off track"}, {"reward_score": 1704, "metric_time": 2473055, "start_time": 2435042, "elapsed_time_in_milliseconds": 38013, "episode": 163, "trial": 3, "phase": "training", "completion_percentage": 73, "episode_status": "Off track"}, {"reward_score": 1638, "metric_time": 2509546, "start_time": 2473133, "elapsed_time_in_milliseconds": 36413, "episode": 164, "trial": 4, "phase": "training", "completion_percentage": 67, "episode_status": "Off track"}, {"reward_score": 1960, "metric_time": 2551261, "start_time": 2509592, "elapsed_time_in_milliseconds": 41669, "episode": 165, "trial": 5, "phase": "training", "completion_percentage": 81, "episode_status": "Off track"}, {"reward_score": 658, "metric_time": 2565486, "start_time": 2551305, "elapsed_time_in_milliseconds": 14181, "episode": 166, "trial": 6, "phase": "training", "completion_percentage": 27, "episode_status": "Off track"}, {"reward_score": 117, "metric_time": 2569409, "start_time": 2565514, "elapsed_time_in_milliseconds": 3895, "episode": 167, "trial": 7, "phase": "training", "completion_percentage": 6, "episode_status": "Off track"}, {"reward_score": 1323, "metric_time": 2600250, "start_time": 2569439, "elapsed_time_in_milliseconds": 30811, "episode": 168, "trial": 8, "phase": "training", "completion_percentage": 58, "episode_status": "Off track"}, {"reward_score": 299, "metric_time": 2606931, "start_time": 2600317, "elapsed_time_in_milliseconds": 6614, "episode": 169, "trial": 9, "phase": "training", "completion_percentage": 13, "episode_status": "Off track"}, {"reward_score": 925, "metric_time": 2625613, "start_time": 2606992, "elapsed_time_in_milliseconds": 18621, "episode": 170, "trial": 10, "phase": "training", "completion_percentage": 35, "episode_status": "Off track"}, {"reward_score": 77, "metric_time": 2628342, "start_time": 2625661, "elapsed_time_in_milliseconds": 2681, "episode": 171, "trial": 11, "phase": "training", "completion_percentage": 3, "episode_status": "Off track"}, {"reward_score": 391, "metric_time": 2639135, "start_time": 2628385, "elapsed_time_in_milliseconds": 10750, "episode": 172, "trial": 12, "phase": "training", "completion_percentage": 17, "episode_status": "Off track"}, {"reward_score": 2260, "metric_time": 2685806, "start_time": 2639190, "elapsed_time_in_milliseconds": 46616, "episode": 173, "trial": 13, "phase": "training", "completion_percentage": 88, "episode_status": "Off track"}, {"reward_score": 399, "metric_time": 2694614, "start_time": 2685844, "elapsed_time_in_milliseconds": 8770, "episode": 174, "trial": 14, "phase": "training", "completion_percentage": 16, "episode_status": "Off track"}, {"reward_score": 216, "metric_time": 2700323, "start_time": 2694651, "elapsed_time_in_milliseconds": 5672, "episode": 175, "trial": 15, "phase": "training", "completion_percentage": 8, "episode_status": "Off track"}, {"reward_score": 137, "metric_time": 2704341, "start_time": 2700392, "elapsed_time_in_milliseconds": 3949, "episode": 176, "trial": 16, "phase": "training", "completion_percentage": 4, "episode_status": "Off track"}, {"reward_score": 636, "metric_time": 2720582, "start_time": 2704402, "elapsed_time_in_milliseconds": 16180, "episode": 177, "trial": 17, "phase": "training", "completion_percentage": 30, "episode_status": "Off track"}, {"reward_score": 664, "metric_time": 2735620, "start_time": 2720663, "elapsed_time_in_milliseconds": 14957, "episode": 178, "trial": 18, "phase": "training", "completion_percentage": 27, "episode_status": "Off track"}, {"reward_score": 1263, "metric_time": 2762890, "start_time": 2735661, "elapsed_time_in_milliseconds": 27229, "episode": 179, "trial": 19, "phase": "training", "completion_percentage": 53, "episode_status": "Off track"}, {"reward_score": 1414, "metric_time": 2792275, "start_time": 2762926, "elapsed_time_in_milliseconds": 29349, "episode": 180, "trial": 20, "phase": "training", "completion_percentage": 59, "episode_status": "Off track"}, {"reward_score": 2032, "metric_time": 2835353, "start_time": 2792387, "elapsed_time_in_milliseconds": 42966, "episode": 180, "trial": 20, "phase": "evaluation", "completion_percentage": 83, "episode_status": "Off track"}, {"reward_score": 207, "metric_time": 2839929, "start_time": 2835390, "elapsed_time_in_milliseconds": 4539, "episode": 180, "trial": 20, "phase": "evaluation", "completion_percentage": 10, "episode_status": "Off track"}, {"reward_score": 983, "metric_time": 2859012, "start_time": 2840000, "elapsed_time_in_milliseconds": 19012, "episode": 180, "trial": 20, "phase": "evaluation", "completion_percentage": 37, "episode_status": "Off track"}, {"reward_score": 1419, "metric_time": 2886170, "start_time": 2859045, "elapsed_time_in_milliseconds": 27125, "episode": 180, "trial": 20, "phase": "evaluation", "completion_percentage": 54, "episode_status": "Off track"}, {"reward_score": 1255, "metric_time": 2911462, "start_time": 2886273, "elapsed_time_in_milliseconds": 25189, "episode": 180, "trial": 20, "phase": "evaluation", "completion_percentage": 53, "episode_status": "Off track"}, {"reward_score": 2713, "metric_time": 2960264, "start_time": 2911515, "elapsed_time_in_milliseconds": 48749, "episode": 180, "trial": 20, "phase": "evaluation", "completion_percentage": 100, "episode_status": "Lap complete"}, {"reward_score": 935, "metric_time": 2979668, "start_time": 2960311, "elapsed_time_in_milliseconds": 19357, "episode": 181, "trial": 1, "phase": "training", "completion_percentage": 37, "episode_status": "Off track"}, {"reward_score": 1956, "metric_time": 3019798, "start_time": 2979727, "elapsed_time_in_milliseconds": 40071, "episode": 182, "trial": 2, "phase": "training", "completion_percentage": 76, "episode_status": "Off track"}, {"reward_score": 1749, "metric_time": 3056990, "start_time": 3019851, "elapsed_time_in_milliseconds": 37139, "episode": 183, "trial": 3, "phase": "training", "completion_percentage": 71, "episode_status": "Off track"}, {"reward_score": 2028, "metric_time": 3102481, "start_time": 3057063, "elapsed_time_in_milliseconds": 45418, "episode": 184, "trial": 4, "phase": "training", "completion_percentage": 85, "episode_status": "Off track"}, {"reward_score": 1627, "metric_time": 3135456, "start_time": 3102512, "elapsed_time_in_milliseconds": 32944, "episode": 185, "trial": 5, "phase": "training", "completion_percentage": 61, "episode_status": "Off track"}, {"reward_score": 1286, "metric_time": 3163783, "start_time": 3135525, "elapsed_time_in_milliseconds": 28258, "episode": 186, "trial": 6, "phase": "training", "completion_percentage": 52, "episode_status": "Off track"}, {"reward_score": 1507, "metric_time": 3196191, "start_time": 3163869, "elapsed_time_in_milliseconds": 32322, "episode": 187, "trial": 7, "phase": "training", "completion_percentage": 62, "episode_status": "Off track"}, {"reward_score": 460, "metric_time": 3208323, "start_time": 3196273, "elapsed_time_in_milliseconds": 12050, "episode": 188, "trial": 8, "phase": "training", "completion_percentage": 22, "episode_status": "Off track"}, {"reward_score": 2115, "metric_time": 3260677, "start_time": 3208392, "elapsed_time_in_milliseconds": 52285, "episode": 189, "trial": 9, "phase": "training", "completion_percentage": 100, "episode_status": "Lap complete"}, {"reward_score": 1662, "metric_time": 3295129, "start_time": 3260724, "elapsed_time_in_milliseconds": 34405, "episode": 190, "trial": 10, "phase": "training", "completion_percentage": 65, "episode_status": "Off track"}, {"reward_score": 707, "metric_time": 3310352, "start_time": 3295191, "elapsed_time_in_milliseconds": 15161, "episode": 191, "trial": 11, "phase": "training", "completion_percentage": 27, "episode_status": "Off track"}, {"reward_score": 1121, "metric_time": 3335954, "start_time": 3310395, "elapsed_time_in_milliseconds": 25559, "episode": 192, "trial": 12, "phase": "training", "completion_percentage": 52, "episode_status": "Off track"}, {"reward_score": 563, "metric_time": 3348096, "start_time": 3335989, "elapsed_time_in_milliseconds": 12107, "episode": 193, "trial": 13, "phase": "training", "completion_percentage": 24, "episode_status": "Off track"}, {"reward_score": 319, "metric_time": 3355257, "start_time": 3348138, "elapsed_time_in_milliseconds": 7119, "episode": 194, "trial": 14, "phase": "training", "completion_percentage": 12, "episode_status": "Off track"}, {"reward_score": 248, "metric_time": 3361819, "start_time": 3355321, "elapsed_time_in_milliseconds": 6498, "episode": 195, "trial": 15, "phase": "training", "completion_percentage": 9, "episode_status": "Off track"}, {"reward_score": 270, "metric_time": 3368398, "start_time": 3361882, "elapsed_time_in_milliseconds": 6516, "episode": 196, "trial": 16, "phase": "training", "completion_percentage": 9, "episode_status": "Off track"}, {"reward_score": 1422, "metric_time": 3398998, "start_time": 3368462, "elapsed_time_in_milliseconds": 30536, "episode": 197, "trial": 17, "phase": "training", "completion_percentage": 59, "episode_status": "Off track"}, {"reward_score": 1345, "metric_time": 3425923, "start_time": 3399044, "elapsed_time_in_milliseconds": 26879, "episode": 198, "trial": 18, "phase": "training", "completion_percentage": 53, "episode_status": "Off track"}, {"reward_score": 2326, "metric_time": 3473684, "start_time": 3426015, "elapsed_time_in_milliseconds": 47669, "episode": 199, "trial": 19, "phase": "training", "completion_percentage": 89, "episode_status": "Off track"}, {"reward_score": 1643, "metric_time": 3509603, "start_time": 3473753, "elapsed_time_in_milliseconds": 35850, "episode": 200, "trial": 20, "phase": "training", "completion_percentage": 66, "episode_status": "Off track"}, {"reward_score": 2622, "metric_time": 3561334, "start_time": 3509742, "elapsed_time_in_milliseconds": 51592, "episode": 200, "trial": 20, "phase": "evaluation", "completion_percentage": 100, "episode_status": "Lap complete"}, {"reward_score": 2521, "metric_time": 3612144, "start_time": 3561383, "elapsed_time_in_milliseconds": 50761, "episode": 200, "trial": 20, "phase": "evaluation", "completion_percentage": 100, "episode_status": "Lap complete"}, {"reward_score": 2265, "metric_time": 3658797, "start_time": 3612207, "elapsed_time_in_milliseconds": 46590, "episode": 200, "trial": 20, "phase": "evaluation", "completion_percentage": 91, "episode_status": "Off track"}, {"reward_score": 2473, "metric_time": 3710144, "start_time": 3658853, "elapsed_time_in_milliseconds": 51291, "episode": 200, "trial": 20, "phase": "evaluation", "completion_percentage": 100, "episode_status": "Lap complete"}, {"reward_score": 2634, "metric_time": 3758827, "start_time": 3710197, "elapsed_time_in_milliseconds": 48630, "episode": 200, "trial": 20, "phase": "evaluation", "completion_percentage": 100, "episode_status": "Lap complete"}, {"reward_score": 2619, "metric_time": 3807589, "start_time": 3758867, "elapsed_time_in_milliseconds": 48722, "episode": 200, "trial": 20, "phase": "evaluation", "completion_percentage": 100, "episode_status": "Lap complete"}, {"reward_score": 41, "metric_time": 3809603, "start_time": 3807667, "elapsed_time_in_milliseconds": 1936, "episode": 201, "trial": 1, "phase": "training", "completion_percentage": 2, "episode_status": "Off track"}, {"reward_score": 220, "metric_time": 3815486, "start_time": 3809656, "elapsed_time_in_milliseconds": 5830, "episode": 202, "trial": 2, "phase": "training", "completion_percentage": 10, "episode_status": "Off track"}, {"reward_score": 968, "metric_time": 3836621, "start_time": 3815528, "elapsed_time_in_milliseconds": 21093, "episode": 203, "trial": 3, "phase": "training", "completion_percentage": 43, "episode_status": "Off track"}, {"reward_score": 1629, "metric_time": 3869682, "start_time": 3836665, "elapsed_time_in_milliseconds": 33017, "episode": 204, "trial": 4, "phase": "training", "completion_percentage": 65, "episode_status": "Off track"}, {"reward_score": 1587, "metric_time": 3905520, "start_time": 3869741, "elapsed_time_in_milliseconds": 35779, "episode": 205, "trial": 5, "phase": "training", "completion_percentage": 70, "episode_status": "Off track"}, {"reward_score": 659, "metric_time": 3920353, "start_time": 3905578, "elapsed_time_in_milliseconds": 14775, "episode": 206, "trial": 6, "phase": "training", "completion_percentage": 27, "episode_status": "Off track"}, {"reward_score": 2465, "metric_time": 3970619, "start_time": 3920395, "elapsed_time_in_milliseconds": 50224, "episode": 207, "trial": 7, "phase": "training", "completion_percentage": 100, "episode_status": "Lap complete"}, {"reward_score": 991, "metric_time": 3993134, "start_time": 3970667, "elapsed_time_in_milliseconds": 22467, "episode": 208, "trial": 8, "phase": "training", "completion_percentage": 43, "episode_status": "Off track"}, {"reward_score": 1412, "metric_time": 4023081, "start_time": 3993215, "elapsed_time_in_milliseconds": 29866, "episode": 209, "trial": 9, "phase": "training", "completion_percentage": 61, "episode_status": "Off track"}, {"reward_score": 362, "metric_time": 4034188, "start_time": 4023121, "elapsed_time_in_milliseconds": 11067, "episode": 210, "trial": 10, "phase": "training", "completion_percentage": 21, "episode_status": "Off track"}, {"reward_score": 761, "metric_time": 4049662, "start_time": 4034264, "elapsed_time_in_milliseconds": 15398, "episode": 211, "trial": 11, "phase": "training", "completion_percentage": 29, "episode_status": "Off track"}, {"reward_score": 668, "metric_time": 4063140, "start_time": 4049728, "elapsed_time_in_milliseconds": 13412, "episode": 212, "trial": 12, "phase": "training", "completion_percentage": 27, "episode_status": "Off track"}, {"reward_score": 610, "metric_time": 4077594, "start_time": 4063217, "elapsed_time_in_milliseconds": 14377, "episode": 213, "trial": 13, "phase": "training", "completion_percentage": 27, "episode_status": "Off track"}, {"reward_score": 2679, "metric_time": 4129400, "start_time": 4077657, "elapsed_time_in_milliseconds": 51743, "episode": 214, "trial": 14, "phase": "training", "completion_percentage": 100, "episode_status": "Lap complete"}, {"reward_score": 358, "metric_time": 4137149, "start_time": 4129468, "elapsed_time_in_milliseconds": 7681, "episode": 215, "trial": 15, "phase": "training", "completion_percentage": 14, "episode_status": "Off track"}, {"reward_score": 173, "metric_time": 4142189, "start_time": 4137187, "elapsed_time_in_milliseconds": 5002, "episode": 216, "trial": 16, "phase": "training", "completion_percentage": 8, "episode_status": "Off track"}, {"reward_score": 415, "metric_time": 4154697, "start_time": 4142275, "elapsed_time_in_milliseconds": 12422, "episode": 217, "trial": 17, "phase": "training", "completion_percentage": 22, "episode_status": "Off track"}, {"reward_score": 2568, "metric_time": 4206472, "start_time": 4154745, "elapsed_time_in_milliseconds": 51727, "episode": 218, "trial": 18, "phase": "training", "completion_percentage": 100, "episode_status": "Lap complete"}, {"reward_score": 2408, "metric_time": 4256280, "start_time": 4206527, "elapsed_time_in_milliseconds": 49753, "episode": 219, "trial": 19, "phase": "training", "completion_percentage": 100, "episode_status": "Lap complete"}, {"reward_score": 240, "metric_time": 4262521, "start_time": 4256346, "elapsed_time_in_milliseconds": 6175, "episode": 220, "trial": 20, "phase": "training", "completion_percentage": 10, "episode_status": "Off track"}, {"reward_score": 2581, "metric_time": 4311990, "start_time": 4262738, "elapsed_time_in_milliseconds": 49252, "episode": 220, "trial": 20, "phase": "evaluation", "completion_percentage": 100, "episode_status": "Lap complete"}, {"reward_score": 1022, "metric_time": 4331594, "start_time": 4312055, "elapsed_time_in_milliseconds": 19539, "episode": 220, "trial": 20, "phase": "evaluation", "completion_percentage": 37, "episode_status": "Off track"}, {"reward_score": 2115, "metric_time": 4372349, "start_time": 4331643, "elapsed_time_in_milliseconds": 40706, "episode": 220, "trial": 20, "phase": "evaluation", "completion_percentage": 78, "episode_status": "Off track"}, {"reward_score": 2135, "metric_time": 4413747, "start_time": 4372392, "elapsed_time_in_milliseconds": 41355, "episode": 220, "trial": 20, "phase": "evaluation", "completion_percentage": 80, "episode_status": "Off track"}, {"reward_score": 2589, "metric_time": 4463932, "start_time": 4413811, "elapsed_time_in_milliseconds": 50121, "episode": 220, "trial": 20, "phase": "evaluation", "completion_percentage": 100, "episode_status": "Lap complete"}, {"reward_score": 2102, "metric_time": 4504522, "start_time": 4463997, "elapsed_time_in_milliseconds": 40525, "episode": 220, "trial": 20, "phase": "evaluation", "completion_percentage": 78, "episode_status": "Off track"}, {"reward_score": 665, "metric_time": 4519204, "start_time": 4504586, "elapsed_time_in_milliseconds": 14618, "episode": 221, "trial": 1, "phase": "training", "completion_percentage": 26, "episode_status": "Off track"}, {"reward_score": 621, "metric_time": 4534082, "start_time": 4519284, "elapsed_time_in_milliseconds": 14798, "episode": 222, "trial": 2, "phase": "training", "completion_percentage": 29, "episode_status": "Off track"}, {"reward_score": 1873, "metric_time": 4573087, "start_time": 4534132, "elapsed_time_in_milliseconds": 38955, "episode": 223, "trial": 3, "phase": "training", "completion_percentage": 71, "episode_status": "Off track"}, {"reward_score": 421, "metric_time": 4582411, "start_time": 4573142, "elapsed_time_in_milliseconds": 9269, "episode": 224, "trial": 4, "phase": "training", "completion_percentage": 16, "episode_status": "Off track"}], "version": 2.0, "best_model_metric": "progress"}